fps_kernel_env/__init__.py
fps_kernel_env/main.py
fps_kernel_env/py.typed
fps_kernel_env/routes.py
fps_kernel_env-0.1.0.dist-info/licenses/LICENSE
fps_kernel_env-0.1.0.dist-info/WHEEL
fps_kernel_env-0.1.0.dist-info/entry_points.txt
fps_kernel_env-0.1.0.dist-info/METADATA
fps_kernel_env-0.1.0.dist-info/RECORD
