Metadata-Version: 2.4
Name: fps_kernel_env
Version: 0.1.0
Summary: An FPS plugin for building kernel environment
Keywords: jupyter,server,fastapi,plugins
Author: Trung Le
License-File: LICENSE
Classifier: Development Status :: 5 - Production/Stable
Classifier: Intended Audience :: Developers
Classifier: License :: OSI Approved :: BSD License
Classifier: Programming Language :: Python
Classifier: Programming Language :: Python :: 3.10
Classifier: Programming Language :: Python :: 3.11
Classifier: Programming Language :: Python :: 3.12
Classifier: Programming Language :: Python :: 3.13
Classifier: Programming Language :: Python :: 3.14
Classifier: Programming Language :: Python :: Implementation :: CPython
Classifier: Programming Language :: Python :: Implementation :: PyPy
Requires-Dist: jupyverse-api>=0.12.0,<0.13.0
Requires-Python: >=3.10
